[
  {
    "src": "assets/stories/IMG_5176.MOV",
    "poster": "assets/stories/posters/IMG_5176.jpg"
  },
  {
    "src": "assets/stories/IMG_5203.MOV",
    "poster": "assets/stories/posters/IMG_5203.jpg"
  },
  {
    "src": "assets/stories/IMG_5252.MP4",
    "poster": "assets/stories/posters/IMG_5252.jpg"
  },
  {
    "src": "assets/stories/IMG_5253.MOV",
    "poster": "assets/stories/posters/IMG_5253.jpg"
  },
  {
    "src": "assets/stories/IMG_5254.MOV",
    "poster": "assets/stories/posters/IMG_5254.jpg"
  },
  {
    "src": "assets/stories/IMG_5554.MOV",
    "poster": "assets/stories/posters/IMG_5554.jpg"
  }
]